{
    "履歴": [
        {
      "date": "20250624135158",
      "データ種別": "emotion",
      "重み": 95,
      "主感情": "自責",
      "構成比": {
        "自責": 50,
        "不安": 25,
        "怒り": 15,
        "悲しみ": 10
      },
      "状況": "猫に与えた薬で体調が悪化した",
      "心理反応": "自分の判断が間違っていたかもしれないという後悔と不安に押しつぶされそうになった",
      "関係性変化": "ペットへのケアがより慎重になり、自己判断に対する警戒心が強まった",
      "関連": [
        "ペットの健康",
        "誤判断",
        "後悔"
      ],
      "keywords": [
        "猫",
        "動物医療",
        "後悔",
        "心配"
      ]
    },
    {
      "date": "20250624134116",
      "データ種別": "emotion",
      "重み": 95,
      "主感情": "自責",
      "構成比": {
        "自責": 55,
        "罪悪感": 45
      },
      "状況": "ポイントが失効していたことに後から気づいたとき",
      "心理反応": "もっと早く気づいていればという後悔が募った",
      "関係性変化": "自己管理や注意深さの重要性を再認識する場面",
      "関連": [
        "損失",
        "管理ミス",
        "後悔"
      ],
      "keywords": [
        "ポイント失効",
        "無駄",
        "後悔"
      ]
    },
    {
      "date": "20250624135940",
      "データ種別": "emotion",
      "重み": 95,
      "主感情": "自責",
      "構成比": {
        "自責": 35,
        "絶望": 25,
        "罪悪感": 20,
        "不安": 20
      },
      "状況": "希望する仕事が見つからなかったとき",
      "心理反応": "自分の能力や価値に疑問を抱き、将来への不安が高まった",
      "関係性変化": "社会的自己評価が下がり、孤独感を感じた",
      "関連": [
        "就職",
        "挫折",
        "不安"
      ],
      "keywords": [
        "仕事探し",
        "見つからない",
        "自責",
        "将来"
      ]
    }
        ]
    }